[
  {"actions": [
    {
      "id": 1,
      "name": "God of War III",
      "year": 2010,
      "price": 20,
      "img": "assets/Images/god_of_war_III.jpg",
      "instock": true,
      "genre": "action", 
      "popul": 95,
      "multiplayer": false
    },
        {
      "id": 2,
      "name": "Grand Theft Auto V",
      "year": 2013,    
      "price": 10,
      "img": "assets/Images/gta5.jpg",
      "instock": true,
      "genre": "action",
      "popul": 93,
      "multiplayer": false    
    },
        {
      "id": 3,
      "name": "Far Cry 3",
      "year": 2012,        
      "price": 7,
      "img": "assets/Images/far_cry.png",
      "instock": true,
      "genre": "action",
      "popul": 89,
      "multiplayer": true
        },
        {
      "id": 4,
      "name": "Uncharted 2: Among Thieves",
      "year": 2009,    
      "price": 15,
      "img": "assets/Images/uncharted2.jpeg",
      "instock": true,
      "genre": "action",
      "popul": 80,
      "multiplayer": false
    },
            {
      "id": 5,
      "name": "Batman: Arkham City",
      "year": 2011,       
      "price": 6,
      "img": "assets/Images/batman.webp",
      "instock": true,
      "genre": "action",
      "popul": 75,
      "multiplayer": false
    },
    {
      "id": 6,
      "name": "Assassins Creed Rogue",
      "year": 2014,
      "price": 6,
      "img": "assets/Images/assassins_creed.jpg",
      "instock": true,
      "genre": "action",
      "popul": 87,
      "multiplayer": false
    },
    {
      "id": 7,
      "name": "Bioshock Infinite",
      "year": 2013,
      "price": 5,
      "img": "assets/Images/bioshock.jpg",
      "instock": true,
      "genre": "action",
      "popul": 60,
      "multiplayer": false
    },
    {
      "id": 8,
      "name": "Call Of Duty Ghosts",
      "year": 2013,
      "price": 6,
      "img": "assets/Images/call_of_duty.jpg",
      "instock": true,
      "genre": "action",
      "popul": 78,
      "multiplayer": true
    },
    {
      "id": 9,
      "name": "Blood Stone 007",
      "year": 2010,
      "price": 6,
      "img": "assets/Images/james_bond.jpg",
      "instock": true,
      "genre": "action",
      "popul": 54,
      "multiplayer": false
    },
    {
      "id": 10,
      "name": "Red Dead Redemption",
      "year": 2010,
      "price": 20,
      "img": "assets/Images/rd_redemption.jpg",
      "instock": true,
      "genre": "action",
      "popul": 89,
      "multiplayer": false
    },
        {
      "id": 11,
      "name": "The Last Of Us",
      "year": 2015,
      "price": 25,
      "img": "assets/Images/the_last_of_us.webp",
      "instock": true,
      "genre": "action",
      "popul": 92,
      "multiplayer": true
    },
        {
      "id": 12,
      "name": "Resident Evil 6",
      "year": 2012,
      "price": 10,
      "img": "assets/Images/resident_evil.webp",
      "instock": true,
      "genre": "action",
      "popul": 81,
      "multiplayer": true
    }
  ]
  },
  {
   "sports": [
     {
      "id": 13,
      "name": "Fifa 18",
      "year": 2017,
      "price": 10,
      "img": "assets/Images/fifa18.jpg",
      "instock": true,
      "genre": "sports",
      "popul": 85,
       "multiplayer": true
     },
     {
      "id": 14,
      "name": "NBA 2K17",
      "year": 2016,
      "price": 15,
      "img": "assets/Images/NBA2K17.jpg",
      "instock": true,
      "genre": "sports",
      "popul": 87,
       "multiplayer": true
     },
     
     {
      "id": 15,
      "name": "NCAA FOOTBALL14",
      "year": 2013,
      "price": 10,
      "img": "assets/Images/ncafootball.jpg",
      "instock": true,
      "genre": "sports",
      "popul": 70,
       "multiplayer": true
     },
     {
      "id": 16,
      "name": "NHL Legacy Edition",
      "year": 2015,
      "price": 15,
      "img": "assets/Images/nhlLE.jpg",
      "instock": true,
      "genre": "sports",
      "popul": 72,
       "multiplayer": true
     },
     {
      "id": 17,
      "name": "PES2018",
      "year": 2017,
      "price": 15,
      "img": "assets/Images/pes2018.jpg",
      "instock": true,
      "genre": "sports",
      "popul": 84,
       "multiplayer": true
     },
     {
      "id": 18,
      "name": "TOPSPIN 4",
      "year": 2011,
      "price": 10,
      "img": "assets/Images/topspin.jpg",
      "instock": true,
      "genre": "sports",
      "popul": 77,
       "multiplayer": true
     },
     {
      "id": 19,
      "name": "WWE 13",
      "year": 2012,
      "price": 10,
      "img": "assets/Images/wwe13.jpg",
      "instock": true,
      "genre": "sports",
      "popul": 69,
       "multiplayer": true
     }
   ] 
  },
  {
   "adventures": [
          {
      "id": 20,
      "name": "Angry Birds Trilogy",
      "year": 2012,
      "price": 10,
      "img": "assets/Images/angry_birds.jpg",
      "instock": true,
      "genre": "adventure",
      "popul": 54,
       "multiplayer": true
     },
     {
      "id": 21,
      "name": "Minecraft",
      "year": 2014,
      "price": 10,
      "img": "assets/Images/minecraft.webp",
      "instock": true,
      "genre": "adventure",
      "popul": 59,
       "multiplayer": false
     },
     {
      "id": 22,
      "name": "Puppeteer",
      "year": 2013,
      "price": 10,
      "img": "assets/Images/puppeteer.jpg",
      "instock": true,
      "genre": "adventure",
      "popul": 47,
       "multiplayer": true
     },
     {
      "id": 23,
      "name": "Ratatouille",
      "year": 2007,
      "price": 10,
      "img": "assets/Images/ratatouille.jpg",
      "instock": true,
      "genre": "adventure",
      "popul": 54,
       "multiplayer": true
     },
     {
      "id": 24,
      "name": "Rayman Legends",
      "year": 2011,
      "price": 10,
      "img": "assets/Images/rayman.jpg",
      "instock": true,
      "genre": "adventure",
      "popul": 60,
       "multiplayer": true
     },
     {
      "id": 25,
      "name": "SONIC Generations",
      "year": 2011,
      "price": 10,
      "img": "assets/Images/sonic.jpg",
      "instock": true,
      "genre": "adventure",
      "popul": 51,
      "multiplayer": false
     },
     {
      "id": 26,
      "name": "The Simpsons",
      "year": 2007,
      "price": 10,
      "img": "assets/Images/the_simpsons.jpg",
      "instock": true,
      "genre": "adventure",
      "popul": 45,
       "multiplayer": true
     }
   ] 
  },
  {
    "racing": [
      {
      "id": 27,
      "name": "Burnout Paradise",
      "year": 2008,
      "price": 10,
      "img": "assets/Images/burnout_paradise.jpg",
      "instock": true,
      "genre": "racing",
      "popul": 52,
       "multiplayer": true
     },
      {
      "id": 28,
      "name": "Dirt 3",
      "year": 2011,
      "price": 15,
      "img": "assets/Images/dirt_3.jpg",
      "instock": true,
      "genre": "racing",
      "popul": 80,
       "multiplayer": true
     },
      {
      "id": 29,
      "name": "Gran Turismo 6",
      "year": 2013,
      "price": 15,
      "img": "assets/Images/gran_turismo_6.jpg",
      "instock": true,
      "genre": "racing",
      "popul": 85,
       "multiplayer": true
     },
      {
      "id": 30,
      "name": "GRID 2",
      "year": 2013,
      "price": 10,
      "img": "assets/Images/grid_2.jpg",
      "instock": true,
      "genre": "racing",
      "popul": 72,
       "multiplayer": true
     },
      {
      "id": 31,
      "name": "NFS Most Wanted",
      "year": 2012,
      "price": 15,
      "img": "assets/Images/need_for_speed_most_wanted.jpg",
      "instock": true,
      "genre": "racing",
      "popul": 52,
       "multiplayer": true
     },
      {
      "id": 32,
      "name": "NFS Rivals COMPLETE EDITION",
      "year": 2013,
      "price": 15,
      "img": "assets/Images/need_for_speed_most_rivals.jpg",
      "instock": true,
      "genre": "racing",
      "popul": 78,
       "multiplayer": true
     }
    ]
  }
  
]
